fattureincloud_python_sdk/__init__.py
fattureincloud_python_sdk/api_client.py
fattureincloud_python_sdk/api_response.py
fattureincloud_python_sdk/configuration.py
fattureincloud_python_sdk/exceptions.py
fattureincloud_python_sdk/py.typed
fattureincloud_python_sdk/rest.py
fattureincloud_python_sdk/api/__init__.py
fattureincloud_python_sdk/api/archive_api.py
fattureincloud_python_sdk/api/cashbook_api.py
fattureincloud_python_sdk/api/clients_api.py
fattureincloud_python_sdk/api/companies_api.py
fattureincloud_python_sdk/api/emails_api.py
fattureincloud_python_sdk/api/info_api.py
fattureincloud_python_sdk/api/issued_documents_api.py
fattureincloud_python_sdk/api/issued_e_invoices_api.py
fattureincloud_python_sdk/api/price_lists_api.py
fattureincloud_python_sdk/api/products_api.py
fattureincloud_python_sdk/api/receipts_api.py
fattureincloud_python_sdk/api/received_documents_api.py
fattureincloud_python_sdk/api/settings_api.py
fattureincloud_python_sdk/api/suppliers_api.py
fattureincloud_python_sdk/api/taxes_api.py
fattureincloud_python_sdk/api/user_api.py
fattureincloud_python_sdk/api/webhooks_api.py
fattureincloud_python_sdk/filter/__init__.py
fattureincloud_python_sdk/filter/condition.py
fattureincloud_python_sdk/filter/conjunction.py
fattureincloud_python_sdk/filter/disjunction.py
fattureincloud_python_sdk/filter/expression.py
fattureincloud_python_sdk/filter/filter.py
fattureincloud_python_sdk/filter/operator.py
fattureincloud_python_sdk/models/__init__.py
fattureincloud_python_sdk/models/archive_document.py
fattureincloud_python_sdk/models/attachment_data.py
fattureincloud_python_sdk/models/cashbook_entry.py
fattureincloud_python_sdk/models/cashbook_entry_document.py
fattureincloud_python_sdk/models/cashbook_entry_kind.py
fattureincloud_python_sdk/models/cashbook_entry_type.py
fattureincloud_python_sdk/models/city.py
fattureincloud_python_sdk/models/client.py
fattureincloud_python_sdk/models/client_type.py
fattureincloud_python_sdk/models/company.py
fattureincloud_python_sdk-2.1.3.dist-info/licenses/LICENSE
fattureincloud_python_sdk-2.1.3.dist-info/METADATA
fattureincloud_python_sdk-2.1.3.dist-info/WHEEL
fattureincloud_python_sdk-2.1.3.dist-info/top_level.txt
fattureincloud_python_sdk-2.1.3.dist-info/RECORD
