Metadata-Version: 2.4
Name: fattureincloud-python-sdk
Version: 2.1.3
Summary: Python SDK for the Fatture in Cloud API
Home-page: https://github.com/fattureincloud/fattureincloud-python-sdk
Author: Fatture in Cloud
Author-email: info@fattureincloud.it
License: MIT
Keywords: fattureincloud,fatture in cloud,fatture,fic,fattureincloud sdk,fatture in cloud sdk
License-File: LICENSE
Requires-Dist: urllib3<3.0.0,>=1.26.8
Requires-Dist: python-dateutil>=2.8.2
Requires-Dist: pydantic>=2
Requires-Dist: typing-extensions>=4.7.1
Dynamic: author
Dynamic: author-email
Dynamic: description
Dynamic: description-content-type
Dynamic: home-page
Dynamic: keywords
Dynamic: license
Dynamic: license-file
Dynamic: requires-dist
Dynamic: summary
